LICENSE.txt
setup.py
code/__init__.py
solacalcu.egg-info/PKG-INFO
solacalcu.egg-info/SOURCES.txt
solacalcu.egg-info/dependency_links.txt
solacalcu.egg-info/top_level.txt